robustnessgym/__init__.py
robustnessgym/version.py
robustnessgym/active/__init__.py
robustnessgym/active/ais.py
robustnessgym/active/mandoline.py
robustnessgym/core/__init__.py
robustnessgym/core/constants.py
robustnessgym/core/dataset_to_task.py
robustnessgym/core/decorators.py
robustnessgym/core/devbench.py
robustnessgym/core/identifier.py
robustnessgym/core/metrics.py
robustnessgym/core/model.py
robustnessgym/core/operation.py
robustnessgym/core/slice.py
robustnessgym/core/storage.py
robustnessgym/core/testbench.py
robustnessgym/core/tools.py
robustnessgym/core/version.py
robustnessgym/demos/__init__.py
robustnessgym/demos/operation.py
robustnessgym/logging/__init__.py
robustnessgym/logging/utils.py
robustnessgym/mixins/__init__.py
robustnessgym/mixins/device.py
robustnessgym/nlp/__init__.py
robustnessgym/ops/__init__.py
robustnessgym/ops/activation.py
robustnessgym/ops/allen.py
robustnessgym/ops/bootleg.py
robustnessgym/ops/similarity.py
robustnessgym/ops/spacy.py
robustnessgym/ops/stanza.py
robustnessgym/ops/strip_text.py
robustnessgym/ops/textblob.py
robustnessgym/report/__init__.py
robustnessgym/report/report.py
robustnessgym/scripts/__init__.py
robustnessgym/scripts/prediction.py
robustnessgym/scripts/qa.py
robustnessgym/slicebuilders/__init__.py
robustnessgym/slicebuilders/attack.py
robustnessgym/slicebuilders/slicebuilder.py
robustnessgym/slicebuilders/slicebuilder_collection.py
robustnessgym/slicebuilders/subpopulation.py
robustnessgym/slicebuilders/subpopulation_collection.py
robustnessgym/slicebuilders/transformation.py
robustnessgym/slicebuilders/attacks/__init__.py
robustnessgym/slicebuilders/attacks/morpheus.py
robustnessgym/slicebuilders/attacks/textattack.py
robustnessgym/slicebuilders/subpopulations/__init__.py
robustnessgym/slicebuilders/subpopulations/constituency_overlap.py
robustnessgym/slicebuilders/subpopulations/entity_frequency.py
robustnessgym/slicebuilders/subpopulations/hans.py
robustnessgym/slicebuilders/subpopulations/length.py
robustnessgym-0.1.3.dist-info/LICENSE.md
robustnessgym-0.1.3.dist-info/METADATA
robustnessgym-0.1.3.dist-info/WHEEL
robustnessgym-0.1.3.dist-info/top_level.txt
robustnessgym-0.1.3.dist-info/RECORD
