Metadata-Version: 2.1
Name: robustnessgym
Version: 0.1.3
Summary: Robustness Gym is an evaluation toolkit for machine learning.
Home-page: https://github.com/robustness-gym/robustness-gym
Author: The Robustness Gym Team
Author-email: kgoel@cs.stanford.edu
License: Apache 2.0
Platform: UNKNOWN
Classifier: Programming Language :: Python
Classifier: Programming Language :: Python :: 3
Classifier: Programming Language :: Python :: 3.6
Classifier: Topic :: Scientific/Engineering :: Artificial Intelligence
Requires-Python: >=3.7.0
Requires-Dist: dataclasses (>=0.6)
Requires-Dist: pandas
Requires-Dist: meerkat-ml (==0.1.2)
Requires-Dist: dill (>=0.3.3)
Requires-Dist: numpy (>=1.18.0)
Requires-Dist: cytoolz
Requires-Dist: ujson
Requires-Dist: transformers
Requires-Dist: fastBPE (>=0.1.0)
Requires-Dist: jsonlines (>=1.2.0)
Requires-Dist: pyahocorasick (>-1.4.0)
Requires-Dist: python-Levenshtein (>=0.12.0)
Requires-Dist: torch (>=1.8.0)
Requires-Dist: tqdm (>=4.49.0)
Requires-Dist: datasets (>=1.4.1)
Requires-Dist: PyYAML (>=5.4.1)
Requires-Dist: omegaconf (>=2.0.5)
Requires-Dist: fuzzywuzzy (>=0.18.0)
Requires-Dist: semver (>=2.13.0)
Requires-Dist: multiprocess (>=0.70.11)
Requires-Dist: Cython (>=0.29.21)
Requires-Dist: progressbar (>=2.5)
Requires-Dist: plotly (>=4.14.1)
Requires-Dist: kaleido (>=0.1.0)
Requires-Dist: pytorch-lightning (>=1.1.2)
Requires-Dist: sklearn
Provides-Extra: adversarial
Requires-Dist: textattack ; extra == 'adversarial'
Provides-Extra: all
Requires-Dist: black (>=21.5b0) ; extra == 'all'
Requires-Dist: isort (>=5.7.0) ; extra == 'all'
Requires-Dist: flake8 (>=3.8.4) ; extra == 'all'
Requires-Dist: docformatter (>=1.4) ; extra == 'all'
Requires-Dist: pytest-cov (>=2.10.1) ; extra == 'all'
Requires-Dist: sphinx-rtd-theme (>=0.5.1) ; extra == 'all'
Requires-Dist: nbsphinx (>=0.8.0) ; extra == 'all'
Requires-Dist: recommonmark (>=0.7.1) ; extra == 'all'
Requires-Dist: pre-commit (>=2.9.3) ; extra == 'all'
Requires-Dist: sphinx-autobuild ; extra == 'all'
Requires-Dist: twine ; extra == 'all'
Requires-Dist: nlpaug (>=1.1.1) ; extra == 'all'
Requires-Dist: textattack ; extra == 'all'
Requires-Dist: nltk ; extra == 'all'
Requires-Dist: textblob ; extra == 'all'
Requires-Dist: spacy ; extra == 'all'
Requires-Dist: stanza ; extra == 'all'
Requires-Dist: allennlp ; extra == 'all'
Requires-Dist: allennlp-models ; extra == 'all'
Requires-Dist: meerkat-ml (==0.1.2[jupyter]) ; extra == 'all'
Requires-Dist: meerkat-ml (==0.1.2[interactive]) ; extra == 'all'
Requires-Dist: rouge-score (>=0.0.4) ; extra == 'all'
Requires-Dist: ludwig ; extra == 'all'
Requires-Dist: tensorflow ; extra == 'all'
Requires-Dist: meerkat-ml (==0.1.2[tabular]) ; extra == 'all'
Requires-Dist: meerkat-ml (==0.1.2[vision]) ; extra == 'all'
Provides-Extra: augmentation
Requires-Dist: nlpaug (>=1.1.1) ; extra == 'augmentation'
Provides-Extra: dev
Requires-Dist: black (>=21.5b0) ; extra == 'dev'
Requires-Dist: isort (>=5.7.0) ; extra == 'dev'
Requires-Dist: flake8 (>=3.8.4) ; extra == 'dev'
Requires-Dist: docformatter (>=1.4) ; extra == 'dev'
Requires-Dist: pytest-cov (>=2.10.1) ; extra == 'dev'
Requires-Dist: sphinx-rtd-theme (>=0.5.1) ; extra == 'dev'
Requires-Dist: nbsphinx (>=0.8.0) ; extra == 'dev'
Requires-Dist: recommonmark (>=0.7.1) ; extra == 'dev'
Requires-Dist: pre-commit (>=2.9.3) ; extra == 'dev'
Requires-Dist: sphinx-autobuild ; extra == 'dev'
Requires-Dist: twine ; extra == 'dev'
Provides-Extra: interactive
Requires-Dist: meerkat-ml (==0.1.2[interactive]) ; extra == 'interactive'
Provides-Extra: jupyter
Requires-Dist: meerkat-ml (==0.1.2[jupyter]) ; extra == 'jupyter'
Provides-Extra: ludwig
Requires-Dist: ludwig ; extra == 'ludwig'
Requires-Dist: tensorflow ; extra == 'ludwig'
Provides-Extra: summarization
Requires-Dist: rouge-score (>=0.0.4) ; extra == 'summarization'
Provides-Extra: tabular
Requires-Dist: meerkat-ml (==0.1.2[tabular]) ; extra == 'tabular'
Provides-Extra: text
Requires-Dist: nltk ; extra == 'text'
Requires-Dist: textblob ; extra == 'text'
Requires-Dist: spacy ; extra == 'text'
Requires-Dist: stanza ; extra == 'text'
Requires-Dist: allennlp ; extra == 'text'
Requires-Dist: allennlp-models ; extra == 'text'
Provides-Extra: vision
Requires-Dist: meerkat-ml (==0.1.2[vision]) ; extra == 'vision'
